README.rst
setup.py
brainslug/__init__.py
brainslug/_slug.py
brainslug/banner.py
brainslug/channel.py
brainslug/database.py
brainslug/remote.py
brainslug/ribosome.py
brainslug/runtime.py
brainslug/web.py
brainslug.egg-info/PKG-INFO
brainslug.egg-info/SOURCES.txt
brainslug.egg-info/dependency_links.txt
brainslug.egg-info/entry_points.txt
brainslug.egg-info/not-zip-safe
brainslug.egg-info/requires.txt
brainslug.egg-info/top_level.txt